tctm/__init__.py
tctm-0.0.2.dist-info/METADATA
tctm-0.0.2.dist-info/WHEEL
tctm-0.0.2.dist-info/top_level.txt
tctm-0.0.2.dist-info/RECORD
