Metadata-Version: 2.1
Name: tctm
Version: 0.0.2
Summary: test lib
Home-page: UNKNOWN
Author: henry
Author-email: enryh123@outlook.com
License: UNKNOWN
Platform: UNKNOWN
Classifier: Programming Language :: Python :: 3
Classifier: License :: OSI Approved :: MIT License
Classifier: Operating System :: OS Independent
Requires-Python: >=3.7
